dicomtrolleytool/__init__.py
dicomtrolleytool/channels.py
dicomtrolleytool/cli/__init__.py
dicomtrolleytool/cli/base.py
dicomtrolleytool/cli/channel.py
dicomtrolleytool/cli/click_parameter_types.py
dicomtrolleytool/cli/download.py
dicomtrolleytool/cli/entrypoint.py
dicomtrolleytool/cli/output.py
dicomtrolleytool/cli/query.py
dicomtrolleytool/exceptions.py
dicomtrolleytool/logs.py
dicomtrolleytool/operations.py
dicomtrolleytool/persistence.py
dicomtrolleytool/query.py
dicomtrolleytool-0.6.1.dist-info/LICENSE
dicomtrolleytool-0.6.1.dist-info/METADATA
dicomtrolleytool-0.6.1.dist-info/WHEEL
dicomtrolleytool-0.6.1.dist-info/entry_points.txt
dicomtrolleytool-0.6.1.dist-info/RECORD
